pytest_docker_pexpect/__init__.py
pytest_docker_pexpect/bare.py
pytest_docker_pexpect/docker.py
pytest_docker_pexpect/plugin.py
pytest_docker_pexpect-0.9.dist-info/METADATA
pytest_docker_pexpect-0.9.dist-info/WHEEL
pytest_docker_pexpect-0.9.dist-info/entry_points.txt
pytest_docker_pexpect-0.9.dist-info/top_level.txt
pytest_docker_pexpect-0.9.dist-info/RECORD
