Metadata-Version: 2.1
Name: pytest-docker-pexpect
Version: 0.9
Summary: pytest plugin for writing functional tests with pexpect and docker
Home-page: https://github.com/nvbn/pytest-docker-pexpect
Author: Vladimir Iakovlev
Author-email: nvbn.rm@gmail.com
License: MIT
Platform: UNKNOWN
Requires-Dist: pexpect
Requires-Dist: pytest
Requires-Dist: six
